forwardAlert4/__init__.py
forwardAlert4/__main__.py
forwardAlert4/alerts.py
forwardAlert4/posts.json
forwardAlert4/requirements.txt
forwardAlert4/runs.py
forwardAlert4/test.ini
forwardAlert4/users.json
forwardAlerts4-0.0.1.dist-info/LICENSE
forwardAlerts4-0.0.1.dist-info/METADATA
forwardAlerts4-0.0.1.dist-info/WHEEL
forwardAlerts4-0.0.1.dist-info/entry_points.txt
forwardAlerts4-0.0.1.dist-info/top_level.txt
forwardAlerts4-0.0.1.dist-info/RECORD
