Metadata-Version: 2.1
Name: forwardAlerts4
Version: 0.0.1
Summary: A forum for fake job postings 
Home-page: UNKNOWN
Author: Ajayi Praise
Author-email: praiseajayi2@gmail.com
License: UNKNOWN
Platform: UNKNOWN
Classifier: Programming Language :: Python :: 3
Classifier: License :: OSI Approved :: MIT License
Classifier: Operating System :: OS Independent
Requires-Python: >=3.6
Requires-Dist: twilio
Requires-Dist: pyfiglet
Requires-Dist: termcolor
